{
  "response": {
    "count": 6,
    "items": [
      {
        "id": 47892,
        "from_id": 229462590,
        "date": 1535564454,
        "text": "Любовь на прокат😍"
      },
      {
        "id": 47907,
        "from_id": 470687935,
        "date": 1535564745,
        "text": "🍀Ребята🍀\n✨Большая просьба✨\n💐Засорять личку💐\n🎀Отправьте что угодно🎀\n🌝Хоть смайлик🌝\n🖤Аудио🖤\n🌸Слово🌸"
      },
      {
        "id": 47963,
        "from_id": 272283581,
        "date": 1535565523,
        "text": "😍❤"
      },
      {
        "id": 47965,
        "from_id": 167614713,
        "date": 1535565549,
        "text": "",
        "attachments": [
          {
            "type": "photo",
            "photo": {
              "id": 456246621,
              "album_id": -8,
              "owner_id": -159071186,
              "user_id": 167614713,
              "sizes": [
                {
                  "type": "m",
                  "url": "https:\/\/sun1-10.userapi.com\/c635104\/v635104696\/3e79d\/14np8pilEMk.jpg",
                  "width": 73,
                  "height": 130
                },
                {
                  "type": "o",
                  "url": "https:\/\/sun1-12.userapi.com\/c635104\/v635104696\/3e7a2\/v8Gbv6xeYM4.jpg",
                  "width": 130,
                  "height": 231
                },
                {
                  "type": "p",
                  "url": "https:\/\/sun1-9.userapi.com\/c635104\/v635104696\/3e7a3\/pXHW0SQ_qXk.jpg",
                  "width": 200,
                  "height": 355
                },
                {
                  "type": "q",
                  "url": "https:\/\/sun1-3.userapi.com\/c635104\/v635104696\/3e7a4\/7YX_HyMCiuI.jpg",
                  "width": 320,
                  "height": 569
                },
                {
                  "type": "r",
                  "url": "https:\/\/sun1-17.userapi.com\/c635104\/v635104696\/3e7a5\/WUYF_aCmOXI.jpg",
                  "width": 510,
                  "height": 900
                },
                {
                  "type": "s",
                  "url": "https:\/\/sun1-3.userapi.com\/c635104\/v635104696\/3e79c\/dRIL2j9P9OY.jpg",
                  "width": 42,
                  "height": 75
                },
                {
                  "type": "w",
                  "url": "https:\/\/sun1-19.userapi.com\/c635104\/v635104696\/3e7a1\/cPVa9KjGgM4.jpg",
                  "width": 720,
                  "height": 1280
                },
                {
                  "type": "x",
                  "url": "https:\/\/sun1-9.userapi.com\/c635104\/v635104696\/3e79e\/IbbkbziZZpo.jpg",
                  "width": 340,
                  "height": 604
                },
                {
                  "type": "y",
                  "url": "https:\/\/sun1-6.userapi.com\/c635104\/v635104696\/3e79f\/iEIYolsmjgQ.jpg",
                  "width": 454,
                  "height": 807
                },
                {
                  "type": "z",
                  "url": "https:\/\/sun1-6.userapi.com\/c635104\/v635104696\/3e7a0\/e1odAmVN6vk.jpg",
                  "width": 607,
                  "height": 1080
                }
              ],
              "text": "",
              "date": 1535565549,
              "access_key": "c3c271bcbe2eb319e9"
            }
          }
        ]
      },
      {
        "id": 48142,
        "from_id": 471741710,
        "date": 1535570134,
        "text": "WTH"
      },
      {
        "id": 48451,
        "from_id": 325782654,
        "date": 1535611557,
        "text": "Омер и Дефне!!❤❤"
      }
    ]
  }
}